{
  "main": {
    "id": "3d1bf937593e9f75",
    "type": "split",
    "children": [
      {
        "id": "79ff329f9e6f44e0",
        "type": "tabs",
        "children": [
          {
            "id": "23c8fd7be79fe55e",
            "type": "leaf",
            "state": {
              "type": "markdown",
              "state": {
                "file": "docs/insights/bilateral.md",
                "mode": "source",
                "source": false
              },
              "icon": "lucide-file",
              "title": "bilateral"
            }
          }
        ]
      }
    ],
    "direction": "vertical"
  },
  "left": {
    "id": "a52143dc30d1355a",
    "type": "split",
    "children": [
      {
        "id": "a35b84d344b6cf35",
        "type": "tabs",
        "children": [
          {
            "id": "69e3b875bcd19714",
            "type": "leaf",
            "state": {
              "type": "file-explorer",
              "state": {
                "sortOrder": "alphabetical",
                "autoReveal": false
              },
              "icon": "lucide-folder-closed",
              "title": "Files"
            }
          },
          {
            "id": "c1846c7b9b948234",
            "type": "leaf",
            "state": {
              "type": "search",
              "state": {
                "query": "",
                "matchingCase": false,
                "explainSearch": false,
                "collapseAll": false,
                "extraContext": false,
                "sortOrder": "alphabetical"
              },
              "icon": "lucide-search",
              "title": "Search"
            }
          },
          {
            "id": "8210bb7123f51bab",
            "type": "leaf",
            "state": {
              "type": "bookmarks",
              "state": {},
              "icon": "lucide-bookmark",
              "title": "Bookmarks"
            }
          }
        ]
      }
    ],
    "direction": "horizontal",
    "width": 300
  },
  "right": {
    "id": "b76508c34b792614",
    "type": "split",
    "children": [
      {
        "id": "d03f08afdbeedc72",
        "type": "tabs",
        "children": [
          {
            "id": "2a90b2bf8cdef625",
            "type": "leaf",
            "state": {
              "type": "backlink",
              "state": {
                "file": "insurance_gemini.md",
                "collapseAll": false,
                "extraContext": false,
                "sortOrder": "alphabetical",
                "showSearch": false,
                "searchQuery": "",
                "backlinkCollapsed": false,
                "unlinkedCollapsed": true
              },
              "icon": "links-coming-in",
              "title": "Backlinks for insurance_gemini"
            }
          },
          {
            "id": "ef9bc6f8c2b7f9b8",
            "type": "leaf",
            "state": {
              "type": "outgoing-link",
              "state": {
                "file": "insurance_gemini.md",
                "linksCollapsed": false,
                "unlinkedCollapsed": true
              },
              "icon": "links-going-out",
              "title": "Outgoing links from insurance_gemini"
            }
          },
          {
            "id": "23d8b79c437dcae9",
            "type": "leaf",
            "state": {
              "type": "tag",
              "state": {
                "sortOrder": "frequency",
                "useHierarchy": true,
                "showSearch": false,
                "searchQuery": ""
              },
              "icon": "lucide-tags",
              "title": "Tags"
            }
          },
          {
            "id": "f7cb8de1f4421073",
            "type": "leaf",
            "state": {
              "type": "all-properties",
              "state": {
                "sortOrder": "frequency",
                "showSearch": false,
                "searchQuery": ""
              },
              "icon": "lucide-archive",
              "title": "All properties"
            }
          },
          {
            "id": "36011a440cfedc49",
            "type": "leaf",
            "state": {
              "type": "outline",
              "state": {
                "file": "insurance_gemini.md",
                "followCursor": false,
                "showSearch": false,
                "searchQuery": ""
              },
              "icon": "lucide-list",
              "title": "Outline of insurance_gemini"
            }
          }
        ]
      }
    ],
    "direction": "horizontal",
    "width": 300,
    "collapsed": true
  },
  "left-ribbon": {
    "hiddenItems": {
      "switcher:Open quick switcher": false,
      "graph:Open graph view": false,
      "canvas:Create new canvas": false,
      "daily-notes:Open today's daily note": false,
      "templates:Insert template": false,
      "command-palette:Open command palette": false,
      "bases:Create new base": false
    }
  },
  "active": "23c8fd7be79fe55e",
  "lastOpenFiles": [
    "playwright-report/data/651ccc192578996fd9c8d30d6e5d0440d739eeef.webm",
    "playwright-report/data/30dcdc07ba0e2650adc22c0c215c8bd81d7560b8.png",
    "tests/test-results/e2e-ahb-payment-E2E-Alice--96f45-tional-payments-through-hub-chromium/video.webm",
    "tests/test-results/e2e-ahb-payment-E2E-Alice--96f45-tional-payments-through-hub-chromium/test-finished-1.png",
    "tests/test-results/e2e-ahb-payment-E2E-Alice--96f45-tional-payments-through-hub-chromium",
    "tests/test-results/08-bob-after-second-payment.png",
    "tests/test-results/07b-alice-after-reverse-receive.png",
    "tests/test-results/07a-bob-after-reverse-send.png",
    "tests/test-results/06b-bob-after-receive.png",
    "tests/test-results/06a-alice-after-send.png",
    "tests/test-results/05-alice-after-faucet.png",
    "tests/test-results/04-alice-connected.png",
    "tests/test-results",
    "db-tmp/runtime/0x68f1544b18bae3d09eff11ca959beb0b407b0e8f/MANIFEST-000538",
    "db-tmp/runtime/0x68f1544b18bae3d09eff11ca959beb0b407b0e8f/000540.log",
    "db-tmp/runtime/0x68f1544b18bae3d09eff11ca959beb0b407b0e8f/000539.ldb",
    "playwright-report/data/04535b516dde697a8b9c95cce3cfee1b2e605711.webm",
    "playwright-report/data/7b6cd15ba9be6914cb12f786c39ef8fcbbe698c2.png",
    "tests/test-results/e2e-runtime-persistence-E2-9ae05--runtimes-and-account-state-chromium/video.webm",
    "tests/test-results/e2e-runtime-persistence-E2-9ae05--runtimes-and-account-state-chromium",
    "db-tmp/runtime/0x68f1544b18bae3d09eff11ca959beb0b407b0e8f/MANIFEST-000535",
    "playwright-report/data/9ba31e3eda8fde2d05b79a46c611bc118efc8188.md",
    "tests/test-results/e2e-ahb-payment-E2E-Alice--96f45-tional-payments-through-hub-chromium/error-context.md",
    "playwright-report/data/9403e0f554db3159c16cdb0e20cf8472629ed3e5.md",
    "playwright-report/data/0d4a709cac3c60413355e43a1d5d6200dbb6dfc5.md",
    "playwright-report/data/995b3a9265de7ac90bffbbd48c0c08d66b730502.md",
    "playwright-report/data/377ed536ccd6db57866706626c3440b37b4911ec.md",
    "playwright-report/data/b7ccfd00f8a2053c1095765a3ce60afbe0aab047.md",
    "playwright-report/data/a690038297efc01d582cd75837f9a9cd4b13592c.md",
    "playwright-report/data/8db04d6af3985c15f806adff00bd0128cb20d7b4.md",
    "playwright-report/data/ee17f33039c7db210bb1e959d5eb6abb5c907f76.md",
    "playwright-report/data/913938daf035822f2303b08f77b17b1610d2c8e4.md",
    "playwright-report/data/9941db848aadef19ed87804bf8e03c85be5611c7.md",
    "playwright-report/data/cb6c4ba23ff086994e240f354d23a64f7c020df9.md",
    "playwright-report/data/5468c7750f5c973787c219aa9cf7e7884673a861.md",
    "playwright-report/data/b6b9a7de0f28a05d8083dd0162880283cb885297.md",
    "playwright-report/data/2ff5f266a854f930b930eb4728fc4d6b7c1525bb.md",
    "playwright-report/data/8895490f7e6ea7585d17f72dfd2014527b0c0bbd.md",
    "playwright-report/data/d9f35bb3b1cdab28f71701e17a8b892cb158aa90.md",
    "playwright-report/data/c926ee11fd60f0c69d0f53bf65ab406ec5c9c1f9.md",
    "tests/test-results/e2e-payment-E2E-HTLC-Payme-2a8ca-ment-through-production-hub-chromium/error-context.md",
    "playwright-report/data/0f0a3a64159a3285f6271f66a7c9dda6c862e746.md",
    "playwright-report/data/6008b05dbcb2c86187d255dfc8222a753bd4b568.md",
    "playwright-report/data/954ffb860116452967b9f87fd27bc854a318ba99.md",
    "playwright-report/data/9ac0771544eda3c87cd1ae0a74f4f99836031ddd.md",
    "playwright-report/data/d845d0bcd6ab21f3c47e3592777722c5aa842e20.md"
  ]
}